[
  {
    "strategy": "AdvancedAdaptive (baseline)",
    "total_trades": 91,
    "winning_trades": 27,
    "losing_trades": 64,
    "win_rate": 0.2967032967032967,
    "profit_factor": 0.772,
    "sharpe_ratio": -3.923,
    "max_drawdown": 0.0483,
    "net_profit": -247.18,
    "total_return_pct": -2.47,
    "avg_trade_pnl": -2.72,
    "avg_win": 31.04,
    "avg_loss": -16.96,
    "largest_win": 53.59,
    "largest_loss": -31.65,
    "avg_hold_hours": 3.8,
    "max_consecutive_losses": 9,
    "total_fees": 355.03,
    "trades_per_day": 4.6,
    "data_days": 20.0,
    "initial_capital": 10000,
    "final_capital": 9575.36
  },
  {
    "strategy": "AdvancedAdaptive (ML agree)",
    "total_trades": 55,
    "winning_trades": 12,
    "losing_trades": 43,
    "win_rate": 0.21818181818181817,
    "profit_factor": 0.615,
    "sharpe_ratio": -5.651,
    "max_drawdown": 0.0448,
    "net_profit": -262.47,
    "total_return_pct": -2.62,
    "avg_trade_pnl": -4.77,
    "avg_win": 34.87,
    "avg_loss": -15.84,
    "largest_win": 47.5,
    "largest_loss": -30.73,
    "avg_hold_hours": 3.7,
    "max_consecutive_losses": 12,
    "total_fees": 214.2,
    "trades_per_day": 2.8,
    "data_days": 20.0,
    "initial_capital": 10000,
    "final_capital": 9630.54
  },
  {
    "strategy": "AdvancedAdaptive (ML veto)",
    "total_trades": 58,
    "winning_trades": 15,
    "losing_trades": 43,
    "win_rate": 0.25862068965517243,
    "profit_factor": 0.685,
    "sharpe_ratio": -4.498,
    "max_drawdown": 0.0421,
    "net_profit": -226.01,
    "total_return_pct": -2.26,
    "avg_trade_pnl": -3.9,
    "avg_win": 32.76,
    "avg_loss": -16.68,
    "largest_win": 51.39,
    "largest_loss": -27.87,
    "avg_hold_hours": 5.1,
    "max_consecutive_losses": 12,
    "total_fees": 225.93,
    "trades_per_day": 2.9,
    "data_days": 20.0,
    "initial_capital": 10000,
    "final_capital": 9661.14
  },
  {
    "strategy": "RSITurbo (baseline)",
    "total_trades": 15,
    "winning_trades": 5,
    "losing_trades": 10,
    "win_rate": 0.3333333333333333,
    "profit_factor": 1.058,
    "sharpe_ratio": 0.38,
    "max_drawdown": 0.009,
    "net_profit": 12.17,
    "total_return_pct": 0.12,
    "avg_trade_pnl": 0.81,
    "avg_win": 44.31,
    "avg_loss": -20.94,
    "largest_win": 53.44,
    "largest_loss": -25.63,
    "avg_hold_hours": 4.8,
    "max_consecutive_losses": 3,
    "total_fees": 59.93,
    "trades_per_day": 0.8,
    "data_days": 20.0,
    "initial_capital": 10000,
    "final_capital": 9982.27
  },
  {
    "strategy": "RSITurbo (ML agree)",
    "total_trades": 11,
    "winning_trades": 3,
    "losing_trades": 8,
    "win_rate": 0.2727272727272727,
    "profit_factor": 0.714,
    "sharpe_ratio": -1.814,
    "max_drawdown": 0.0145,
    "net_profit": -49.69,
    "total_return_pct": -0.5,
    "avg_trade_pnl": -4.52,
    "avg_win": 41.41,
    "avg_loss": -21.74,
    "largest_win": 51.92,
    "largest_loss": -25.63,
    "avg_hold_hours": 4.2,
    "max_consecutive_losses": 4,
    "total_fees": 43.71,
    "trades_per_day": 0.6,
    "data_days": 20.0,
    "initial_capital": 10000,
    "final_capital": 9928.48
  },
  {
    "strategy": "RSITurbo (ML veto)",
    "total_trades": 12,
    "winning_trades": 3,
    "losing_trades": 9,
    "win_rate": 0.25,
    "profit_factor": 0.623,
    "sharpe_ratio": -2.7,
    "max_drawdown": 0.0173,
    "net_profit": -75.17,
    "total_return_pct": -0.75,
    "avg_trade_pnl": -6.26,
    "avg_win": 41.32,
    "avg_loss": -22.13,
    "largest_win": 51.77,
    "largest_loss": -25.63,
    "avg_hold_hours": 5.3,
    "max_consecutive_losses": 5,
    "total_fees": 47.59,
    "trades_per_day": 0.6,
    "data_days": 20.0,
    "initial_capital": 10000,
    "final_capital": 9901.05
  },
  {
    "strategy": "SuperTrend (baseline)",
    "total_trades": 30,
    "winning_trades": 10,
    "losing_trades": 20,
    "win_rate": 0.3333333333333333,
    "profit_factor": 1.065,
    "sharpe_ratio": 0.574,
    "max_drawdown": 0.0104,
    "net_profit": 21.8,
    "total_return_pct": 0.22,
    "avg_trade_pnl": 0.73,
    "avg_win": 35.9,
    "avg_loss": -16.86,
    "largest_win": 55.19,
    "largest_loss": -26.51,
    "avg_hold_hours": 6.8,
    "max_consecutive_losses": 5,
    "total_fees": 119.52,
    "trades_per_day": 1.5,
    "data_days": 20.0,
    "initial_capital": 10000,
    "final_capital": 9961.92
  },
  {
    "strategy": "SuperTrend (ML agree)",
    "total_trades": 5,
    "winning_trades": 2,
    "losing_trades": 3,
    "win_rate": 0.4,
    "profit_factor": 1.128,
    "sharpe_ratio": 0.468,
    "max_drawdown": 0.0029,
    "net_profit": 8.36,
    "total_return_pct": 0.08,
    "avg_trade_pnl": 1.67,
    "avg_win": 36.93,
    "avg_loss": -21.83,
    "largest_win": 44.41,
    "largest_loss": -26.66,
    "avg_hold_hours": 17.1,
    "max_consecutive_losses": 1,
    "total_fees": 19.96,
    "trades_per_day": 0.3,
    "data_days": 20.0,
    "initial_capital": 10000,
    "final_capital": 9998.36
  },
  {
    "strategy": "SuperTrend (ML veto)",
    "total_trades": 14,
    "winning_trades": 4,
    "losing_trades": 10,
    "win_rate": 0.2857142857142857,
    "profit_factor": 0.643,
    "sharpe_ratio": -2.812,
    "max_drawdown": 0.0103,
    "net_profit": -75.26,
    "total_return_pct": -0.75,
    "avg_trade_pnl": -5.38,
    "avg_win": 33.92,
    "avg_loss": -21.09,
    "largest_win": 44.21,
    "largest_loss": -28.03,
    "avg_hold_hours": 11.0,
    "max_consecutive_losses": 4,
    "total_fees": 55.77,
    "trades_per_day": 0.7,
    "data_days": 20.0,
    "initial_capital": 10000,
    "final_capital": 9896.88
  },
  {
    "strategy": "MACrossover (baseline)",
    "total_trades": 41,
    "winning_trades": 11,
    "losing_trades": 30,
    "win_rate": 0.2682926829268293,
    "profit_factor": 0.53,
    "sharpe_ratio": -6.789,
    "max_drawdown": 0.032,
    "net_profit": -239.39,
    "total_return_pct": -2.39,
    "avg_trade_pnl": -5.84,
    "avg_win": 24.58,
    "avg_loss": -16.99,
    "largest_win": 48.44,
    "largest_loss": -24.48,
    "avg_hold_hours": 5.1,
    "max_consecutive_losses": 8,
    "total_fees": 161.06,
    "trades_per_day": 2.1,
    "data_days": 20.0,
    "initial_capital": 10000,
    "final_capital": 9680.03
  },
  {
    "strategy": "MACrossover (ML agree)",
    "total_trades": 6,
    "winning_trades": 0,
    "losing_trades": 6,
    "win_rate": 0.0,
    "profit_factor": 0.0,
    "sharpe_ratio": -23.476,
    "max_drawdown": 0.0084,
    "net_profit": -72.53,
    "total_return_pct": -0.73,
    "avg_trade_pnl": -12.09,
    "avg_win": 0,
    "avg_loss": -12.09,
    "largest_win": -6.88,
    "largest_loss": -18.01,
    "avg_hold_hours": 4.1,
    "max_consecutive_losses": 6,
    "total_fees": 23.88,
    "trades_per_day": 0.3,
    "data_days": 20.0,
    "initial_capital": 10000,
    "final_capital": 9915.51
  },
  {
    "strategy": "MACrossover (ML veto)",
    "total_trades": 17,
    "winning_trades": 5,
    "losing_trades": 12,
    "win_rate": 0.29411764705882354,
    "profit_factor": 0.506,
    "sharpe_ratio": -4.68,
    "max_drawdown": 0.0135,
    "net_profit": -98.28,
    "total_return_pct": -0.98,
    "avg_trade_pnl": -5.78,
    "avg_win": 20.12,
    "avg_loss": -16.57,
    "largest_win": 37.36,
    "largest_loss": -24.53,
    "avg_hold_hours": 4.0,
    "max_consecutive_losses": 6,
    "total_fees": 67.57,
    "trades_per_day": 0.9,
    "data_days": 20.0,
    "initial_capital": 10000,
    "final_capital": 9867.96
  },
  {
    "strategy": "MomentumPro (baseline)",
    "total_trades": 64,
    "winning_trades": 16,
    "losing_trades": 48,
    "win_rate": 0.25,
    "profit_factor": 0.611,
    "sharpe_ratio": -6.401,
    "max_drawdown": 0.0466,
    "net_profit": -341.34,
    "total_return_pct": -3.41,
    "avg_trade_pnl": -5.33,
    "avg_win": 33.58,
    "avg_loss": -18.3,
    "largest_win": 51.67,
    "largest_loss": -28.58,
    "avg_hold_hours": 5.5,
    "max_consecutive_losses": 10,
    "total_fees": 249.22,
    "trades_per_day": 3.3,
    "data_days": 20.0,
    "initial_capital": 10000,
    "final_capital": 9534.04
  },
  {
    "strategy": "MomentumPro (ML agree)",
    "total_trades": 39,
    "winning_trades": 10,
    "losing_trades": 29,
    "win_rate": 0.2564102564102564,
    "profit_factor": 0.775,
    "sharpe_ratio": -2.444,
    "max_drawdown": 0.0304,
    "net_profit": -104.61,
    "total_return_pct": -1.05,
    "avg_trade_pnl": -2.68,
    "avg_win": 36.08,
    "avg_loss": -16.05,
    "largest_win": 48.49,
    "largest_loss": -30.85,
    "avg_hold_hours": 3.3,
    "max_consecutive_losses": 11,
    "total_fees": 153.36,
    "trades_per_day": 2.0,
    "data_days": 20.0,
    "initial_capital": 10000,
    "final_capital": 9818.78
  },
  {
    "strategy": "MomentumPro (ML veto)",
    "total_trades": 47,
    "winning_trades": 13,
    "losing_trades": 34,
    "win_rate": 0.2765957446808511,
    "profit_factor": 0.765,
    "sharpe_ratio": -2.93,
    "max_drawdown": 0.0276,
    "net_profit": -144.25,
    "total_return_pct": -1.44,
    "avg_trade_pnl": -3.07,
    "avg_win": 36.2,
    "avg_loss": -18.08,
    "largest_win": 51.59,
    "largest_loss": -27.97,
    "avg_hold_hours": 5.5,
    "max_consecutive_losses": 6,
    "total_fees": 185.29,
    "trades_per_day": 2.4,
    "data_days": 20.0,
    "initial_capital": 10000,
    "final_capital": 9763.19
  }
]